[{"Code":"BOGA","Name":"Bintang Oto Global T","BFreq":"13","BVol":"68000","BVal":"96.3 M","BAvg":"1416.18","SFreq":"23","SVol":"46.13 M","SVal":"64.81 B","SAvg":"1405.02","NVol":"46.06 M","NVal":"64.72 B","CVol":"68000","CVal":"96.3 M","TFreq":"36","TVol":"46.2 M","TVal":"64.91 B","TAvg":"1405.04","broker_code":"PO","date":"21 Feb 2022"},{"Code":"NATO","Name":"Surya Permata Andala","BFreq":"188","BVol":"33.72 M","BVal":"25.16 B","BAvg":"746.15","SFreq":"71","SVol":"44.19 M","SVal":"32.67 B","SAvg":"739.41","NVol":"10.47 M","NVal":"7.51 B","CVol":"33.72 M","CVal":"25.16 B","TFreq":"259","TVol":"77.91 M","TVal":"57.83 B","TAvg":"742.33","broker_code":"PO","date":"21 Feb 2022"},{"Code":"CARE","Name":"Metro Healthcare Ind","BFreq":"16","BVol":"5.48 M","BVal":"3.15 B","BAvg":"574.45","SFreq":"172","SVol":"43.46 M","SVal":"24.36 B","SAvg":"560.62","NVol":"37.98 M","NVal":"21.22 B","CVol":"5.48 M","CVal":"3.15 B","TFreq":"188","TVol":"48.93 M","TVal":"27.51 B","TAvg":"562.17","broker_code":"PO","date":"21 Feb 2022"},{"Code":"STAR","Name":"Buana Artha Anugerah","BFreq":"","BVol":"1","BVal":"16.0 M","BAvg":"2.32 B","SFreq":"145.00","SVol":"16.0 M","SVal":"2.32 B","SAvg":"","NVol":"1","NVal":"16.0 M","CVol":"2.32 B","CVal":"145.00","broker_code":"PO","date":"21 Feb 2022"},{"Code":"ZINC","Name":"Kapuas Prima Coal Tb","BFreq":"52","BVol":"13.7 M","BVal":"1.43 B","BAvg":"104.31","SFreq":"150","SVol":"13.7 M","SVal":"1.43 B","SAvg":"104.61","NVol":"0","NVal":"4.0 M","CVol":"13.7 M","CVal":"1.43 B","TFreq":"202","TVol":"27.4 M","TVal":"2.86 B","TAvg":"104.46","broker_code":"PO","date":"21 Feb 2022"},{"Code":"PSGO","Name":"Palma Serasih Tbk.","BFreq":"80","BVol":"806900","BVal":"156.71 M","BAvg":"194.22","SFreq":"235","SVol":"1.94 M","SVal":"383.09 M","SAvg":"197.23","NVol":"1.14 M","NVal":"226.38 M","CVol":"806900","CVal":"156.71 M","TFreq":"315","TVol":"2.75 M","TVal":"539.8 M","TAvg":"196.34","broker_code":"PO","date":"21 Feb 2022"},{"Code":"ADRO","Name":"Adaro Energy Indones","BFreq":"47","BVol":"1.23 M","BVal":"2.73 B","BAvg":"2227.14","SFreq":"84","SVol":"1.23 M","SVal":"2.73 B","SAvg":"2227.14","NVol":"100","NVal":"222000","CVol":"1.23 M","CVal":"2.73 B","TFreq":"131","TVol":"2.45 M","TVal":"5.46 B","TAvg":"2227.14","broker_code":"PO","date":"21 Feb 2022"},{"Code":"MDKA","Name":"Merdeka Copper Gold","BFreq":"21","BVol":"875000","BVal":"3.38 B","BAvg":"3858.00","SFreq":"57","SVol":"875000","SVal":"3.37 B","SAvg":"3856.00","NVol":"0","NVal":"1.75 M","CVol":"875000","CVal":"3.37 B","TFreq":"78","TVol":"1.75 M","TVal":"6.75 B","TAvg":"3857.00","broker_code":"PO","date":"21 Feb 2022"},{"Code":"MIKA","Name":"Mitra Keluarga Karya","BFreq":"118","BVol":"795100","BVal":"1.77 B","BAvg":"2229.24","SFreq":"57","SVol":"809400","SVal":"1.8 B","SAvg":"2230.02","NVol":"14300","NVal":"32.51 M","CVol":"795100","CVal":"1.77 B","TFreq":"175","TVol":"1.6 M","TVal":"3.58 B","TAvg":"2229.64","broker_code":"PO","date":"21 Feb 2022"},{"Code":"ADMR","Name":"Adaro Minerals Indon","BFreq":"24","BVol":"700000","BVal":"823.38 M","BAvg":"1176.25","SFreq":"42","SVol":"658800","SVal":"772.29 M","SAvg":"1172.27","NVol":"41200","NVal":"51.09 M","CVol":"658800","CVal":"772.29 M","TFreq":"66","TVol":"1.36 M","TVal":"1.6 B","TAvg":"1174.32","broker_code":"PO","date":"21 Feb 2022"},{"Code":"ARTO","Name":"Bank Jago Tbk.","BFreq":"98","BVol":"630000","BVal":"10.03 B","BAvg":"15913.89","SFreq":"105","SVol":"630000","SVal":"10.02 B","SAvg":"15901.39","NVol":"0","NVal":"7.88 M","CVol":"630000","CVal":"10.02 B","TFreq":"203","TVol":"1.26 M","TVal":"20.04 B","TAvg":"15907.64","broker_code":"PO","date":"21 Feb 2022"},{"Code":"DRMA","Name":"Dharma Polimetal Tbk","BFreq":"70","BVol":"834000","BVal":"501.01 M","BAvg":"600.73","SFreq":"42","SVol":"483000","SVal":"291.61 M","SAvg":"603.75","NVol":"351000","NVal":"209.4 M","CVol":"483000","CVal":"291.61 M","TFreq":"112","TVol":"1.32 M","TVal":"792.62 M","TAvg":"601.83","broker_code":"PO","date":"21 Feb 2022"},{"Code":"TRJA","Name":"Transkon Jaya Tbk.","BFreq":"22","BVol":"270000","BVal":"117.72 M","BAvg":"436.00","SFreq":"18","SVol":"470000","SVal":"205.26 M","SAvg":"436.72","NVol":"200000","NVal":"87.54 M","CVol":"270000","CVal":"117.72 M","TFreq":"40","TVol":"740000","TVal":"322.98 M","TAvg":"436.46","broker_code":"PO","date":"21 Feb 2022"},{"Code":"MARK","Name":"Mark Dynamics Indone","BFreq":"9","BVol":"49000","BVal":"53.98 M","BAvg":"1101.63","SFreq":"81","SVol":"378900","SVal":"417.35 M","SAvg":"1101.47","NVol":"329900","NVal":"363.37 M","CVol":"49000","CVal":"53.98 M","TFreq":"90","TVol":"427900","TVal":"471.33 M","TAvg":"1101.49","broker_code":"PO","date":"21 Feb 2022"},{"Code":"MGRO","Name":"Mahkota Group Tbk.","BFreq":"9","BVol":"55600","BVal":"48.9 M","BAvg":"879.45","SFreq":"17","SVol":"364200","SVal":"319.36 M","SAvg":"876.89","NVol":"308600","NVal":"270.47 M","CVol":"55600","CVal":"48.9 M","TFreq":"26","TVol":"419800","TVal":"368.26 M","TAvg":"877.23","broker_code":"PO","date":"21 Feb 2022"},{"Code":"TAPG","Name":"Triputra Agro Persad","BFreq":"8","BVol":"350000","BVal":"255.5 M","BAvg":"730.00","SFreq":"26","SVol":"350000","SVal":"255.5 M","SAvg":"730.00","NVol":"0","NVal":"0","CVol":"350000","CVal":"255.5 M","TFreq":"34","TVol":"700000","TVal":"511.0 M","TAvg":"730.00","broker_code":"PO","date":"21 Feb 2022"},{"Code":"ALDO","Name":"Alkindo Naratama Tbk","BFreq":"11","BVol":"60000","BVal":"70.38 M","BAvg":"1173.00","SFreq":"42","SVol":"316900","SVal":"369.1 M","SAvg":"1164.72","NVol":"256900","NVal":"298.72 M","CVol":"60000","CVal":"70.38 M","TFreq":"53","TVol":"376900","TVal":"439.48 M","TAvg":"1166.04","broker_code":"PO","date":"21 Feb 2022"},{"Code":"APIC","Name":"Pacific Strategic Fi","BFreq":"6","BVol":"112000","BVal":"131.82 M","BAvg":"1176.96","SFreq":"12","SVol":"243500","SVal":"286.6 M","SAvg":"1176.99","NVol":"131500","NVal":"154.78 M","CVol":"112000","CVal":"131.82 M","TFreq":"18","TVol":"355500","TVal":"418.42 M","TAvg":"1176.98","broker_code":"PO","date":"21 Feb 2022"},{"Code":"BMHS","Name":"Bundamedik Tbk.","BFreq":"4","BVol":"200000","BVal":"143.0 M","BAvg":"715.00","SFreq":"5","SVol":"200000","SVal":"143.0 M","SAvg":"715.00","NVol":"0","NVal":"0","CVol":"200000","CVal":"143.0 M","TFreq":"9","TVol":"400000","TVal":"286.0 M","TAvg":"715.00","broker_code":"PO","date":"21 Feb 2022"},{"Code":"IMPC","Name":"Impack Pratama Indus","BFreq":"22","BVol":"150000","BVal":"418.9 M","BAvg":"2792.67","SFreq":"31","SVol":"150000","SVal":"421.1 M","SAvg":"2807.33","NVol":"0","NVal":"2.2 M","CVol":"150000","CVal":"418.9 M","TFreq":"53","TVol":"300000","TVal":"840.0 M","TAvg":"2800.00","broker_code":"PO","date":"21 Feb 2022"},{"Code":"BAUT","Name":"Mitra Angkasa Sejaht","BFreq":"12","BVol":"147000","BVal":"27.99 M","BAvg":"190.39","SFreq":"13","SVol":"119500","SVal":"23.42 M","SAvg":"196.01","NVol":"27500","NVal":"4.57 M","CVol":"119500","CVal":"23.42 M","TFreq":"25","TVol":"266500","TVal":"51.41 M","TAvg":"192.91","broker_code":"PO","date":"21 Feb 2022"},{"Code":"EAST-W","Name":"EAST-W 20220708","BFreq":"12","BVol":"125100","BVal":"1.0 M","BAvg":"8.00","SFreq":"1","SVol":"110800","SVal":"997200","SAvg":"9.00","NVol":"14300","NVal":"3600","CVol":"110800","CVal":"997200","TFreq":"13","TVol":"235900","TVal":"2.0 M","TAvg":"8.47","broker_code":"PO","date":"21 Feb 2022"},{"Code":"IATA","Name":"Indonesia Transport","BFreq":"1","BVol":"500","BVal":"87000","BAvg":"174.00","SFreq":"9","SVol":"110000","SVal":"21.35 M","SAvg":"194.06","NVol":"109500","NVal":"21.26 M","CVol":"500","CVal":"87000","TFreq":"10","TVol":"110500","TVal":"21.43 M","TAvg":"193.97","broker_code":"PO","date":"21 Feb 2022"},{"Code":"DOID","Name":"Delta Dunia Makmur T","BFreq":"","BVol":"5","BVal":"100100","BAvg":"36.38 M","SFreq":"363.40","SVol":"100100","SVal":"36.38 M","SAvg":"","NVol":"5","NVal":"100100","CVol":"36.38 M","CVal":"363.40","broker_code":"PO","date":"21 Feb 2022"},{"Code":"TBIG","Name":"Tower Bersama Infras","BFreq":"2","BVol":"100000","BVal":"294.0 M","BAvg":"2940.00","SFreq":"3","SVol":"100000","SVal":"294.0 M","SAvg":"2940.00","NVol":"0","NVal":"0","CVol":"100000","CVal":"294.0 M","TFreq":"5","TVol":"200000","TVal":"588.0 M","TAvg":"2940.00","broker_code":"PO","date":"21 Feb 2022"},{"Code":"ERAA","Name":"Erajaya Swasembada T","BFreq":"","BVol":"1","BVal":"100000","BAvg":"58.5 M","SFreq":"585.00","SVol":"100000","SVal":"58.5 M","SAvg":"","NVol":"1","NVal":"100000","CVol":"58.5 M","CVal":"585.00","broker_code":"PO","date":"21 Feb 2022"},{"Code":"BRMS","Name":"Bumi Resources Miner","BFreq":"1","BVol":"100000","BVal":"16.5 M","BAvg":"165.00","SFreq":"1","SVol":"100000","SVal":"17.2 M","SAvg":"172.00","NVol":"0","NVal":"700000","CVol":"100000","CVal":"16.5 M","TFreq":"2","TVol":"200000","TVal":"33.7 M","TAvg":"168.50","broker_code":"PO","date":"21 Feb 2022"},{"Code":"PSKT","Name":"Red Planet Indonesia","BFreq":"","BVol":"4","BVal":"50000","BAvg":"5.85 M","SFreq":"117.00","SVol":"50000","SVal":"5.85 M","SAvg":"","NVol":"4","NVal":"50000","CVol":"5.85 M","CVal":"117.00","broker_code":"PO","date":"21 Feb 2022"},{"Code":"SQMI","Name":"Wilton Makmur Indone","BFreq":"","BVol":"1","BVal":"40000","BAvg":"3.84 M","SFreq":"96.00","SVol":"40000","SVal":"3.84 M","SAvg":"","NVol":"1","NVal":"40000","CVol":"3.84 M","CVal":"96.00","broker_code":"PO","date":"21 Feb 2022"},{"Code":"MCOR","Name":"Bank China Constr. B","BFreq":"","BVol":"6","BVal":"30000","BAvg":"3.15 M","SFreq":"105.00","SVol":"30000","SVal":"3.15 M","SAvg":"","NVol":"6","NVal":"30000","CVol":"3.15 M","CVal":"105.00","broker_code":"PO","date":"21 Feb 2022"},{"Code":"NELY","Name":"Pelayaran Nelly Dwi","BFreq":"","BVol":"3","BVal":"30000","BAvg":"9.37 M","SFreq":"312.33","SVol":"30000","SVal":"9.37 M","SAvg":"","NVol":"3","NVal":"30000","CVol":"9.37 M","CVal":"312.33","broker_code":"PO","date":"21 Feb 2022"},{"Code":"BAPA","Name":"Bekasi Asri Pemula T","BFreq":"3","BVol":"21000","BVal":"2.98 M","BAvg":"141.67","SFreq":"3","SVol":"20000","SVal":"2.89 M","SAvg":"144.50","NVol":"1000","NVal":"85000","CVol":"20000","CVal":"2.89 M","TFreq":"6","TVol":"41000","TVal":"5.87 M","TAvg":"143.05","broker_code":"PO","date":"21 Feb 2022"},{"Code":"KPIG","Name":"MNC Land Tbk","BFreq":"1","BVol":"2500","BVal":"322500","BAvg":"129.00","SFreq":"4","SVol":"15400","SVal":"2.07 M","SAvg":"134.55","NVol":"12900","NVal":"1.75 M","CVol":"2500","CVal":"322500","TFreq":"5","TVol":"17900","TVal":"2.39 M","TAvg":"133.77","broker_code":"PO","date":"21 Feb 2022"},{"Code":"WIKA","Name":"Wijaya Karya (Perser","BFreq":"3","BVol":"27600","BVal":"31.72 M","BAvg":"1149.40","SFreq":"2","SVol":"14700","SVal":"16.86 M","SAvg":"1146.80","NVol":"12900","NVal":"14.87 M","CVol":"14700","CVal":"16.86 M","TFreq":"5","TVol":"42300","TVal":"48.58 M","TAvg":"1148.50","broker_code":"PO","date":"21 Feb 2022"},{"Code":"PTPW","Name":"Pratama Widya Tbk.","BFreq":"4","BVol":"5700","BVal":"4.56 M","BAvg":"800.09","SFreq":"8","SVol":"12900","SVal":"10.21 M","SAvg":"791.55","NVol":"7200","NVal":"5.65 M","CVol":"5700","CVal":"4.56 M","TFreq":"12","TVol":"18600","TVal":"14.77 M","TAvg":"794.17","broker_code":"PO","date":"21 Feb 2022"},{"Code":"PTBA","Name":"Bukit Asam Tbk","BFreq":"","BVol":"1","BVal":"5600","BAvg":"16.58 M","SFreq":"2960.00","SVol":"5600","SVal":"16.58 M","SAvg":"","NVol":"1","NVal":"5600","CVol":"16.58 M","CVal":"2960.00","broker_code":"PO","date":"21 Feb 2022"},{"Code":"EMTK","Name":"Elang Mahkota Teknol","BFreq":"","BVol":"1","BVal":"5000","BAvg":"10.0 M","SFreq":"2000.00","SVol":"5000","SVal":"10.0 M","SAvg":"","NVol":"1","NVal":"5000","CVol":"10.0 M","CVal":"2000.00","broker_code":"PO","date":"21 Feb 2022"},{"Code":"BWPT","Name":"Eagle High Plantatio","BFreq":"","BVol":"3","BVal":"3300","BAvg":"297000","SFreq":"90.00","SVol":"3300","SVal":"297000","SAvg":"","NVol":"3","NVal":"3300","CVol":"297000","CVal":"90.00","broker_code":"PO","date":"21 Feb 2022"},{"Code":"PALM","Name":"Provident Agro Tbk.","BFreq":"","BVol":"1","BVal":"3200","BAvg":"2.29 M","SFreq":"715.00","SVol":"3200","SVal":"2.29 M","SAvg":"","NVol":"1","NVal":"3200","CVol":"2.29 M","CVal":"715.00","broker_code":"PO","date":"21 Feb 2022"},{"Code":"TRIN","Name":"Perintis Triniti Pro","BFreq":"","BVol":"1","BVal":"3000","BAvg":"1.92 M","SFreq":"640.00","SVol":"3000","SVal":"1.92 M","SAvg":"","NVol":"1","NVal":"3000","CVol":"1.92 M","CVal":"640.00","broker_code":"PO","date":"21 Feb 2022"},{"Code":"BNGA","Name":"Bank CIMB Niaga Tbk","BFreq":"","BVol":"2","BVal":"2200","BAvg":"2.22 M","SFreq":"1009.55","SVol":"2200","SVal":"2.22 M","SAvg":"","NVol":"2","NVal":"2200","CVol":"2.22 M","CVal":"1009.55","broker_code":"PO","date":"21 Feb 2022"},{"Code":"BBYB","Name":"Bank Neo Commerce Tb","BFreq":"","BVol":"2","BVal":"2000","BAvg":"4.86 M","SFreq":"2430.00","SVol":"2000","SVal":"4.86 M","SAvg":"","NVol":"2","NVal":"2000","CVol":"4.86 M","CVal":"2430.00","broker_code":"PO","date":"21 Feb 2022"},{"Code":"MNCN","Name":"Media Nusantara Citr","BFreq":"2","BVol":"3400","BVal":"3.09 M","BAvg":"910.00","SFreq":"1","SVol":"1700","SVal":"1.56 M","SAvg":"915.00","NVol":"1700","NVal":"1.54 M","CVol":"1700","CVal":"1.56 M","TFreq":"3","TVol":"5100","TVal":"4.65 M","TAvg":"911.67","broker_code":"PO","date":"21 Feb 2022"},{"Code":"BUKA","Name":"Bukalapak.com Tbk.","BFreq":"1","BVol":"1000","BVal":"364000","BAvg":"364.00","SFreq":"1","SVol":"1000","SVal":"362000","SAvg":"362.00","NVol":"0","NVal":"2000","CVol":"1000","CVal":"362000","TFreq":"2","TVol":"2000","TVal":"726000","TAvg":"363.00","broker_code":"PO","date":"21 Feb 2022"},{"Code":"ANTM","Name":"Aneka Tambang Tbk","BFreq":"","BVol":"1","BVal":"1000","BAvg":"2.16 M","SFreq":"2160.00","SVol":"1000","SVal":"2.16 M","SAvg":"","NVol":"1","NVal":"1000","CVol":"2.16 M","CVal":"2160.00","broker_code":"PO","date":"21 Feb 2022"},{"Code":"BRIS","Name":"Bank Syariah Indones","BFreq":"","BVol":"1","BVal":"1000","BAvg":"1.74 M","SFreq":"1735.00","SVol":"1000","SVal":"1.74 M","SAvg":"","NVol":"1","NVal":"1000","CVol":"1.74 M","CVal":"1735.00","broker_code":"PO","date":"21 Feb 2022"},{"Code":"BABP","Name":"Bank MNC Internasion","BFreq":"","BVol":"1","BVal":"1000","BAvg":"242000","SFreq":"242.00","SVol":"1000","SVal":"242000","SAvg":"","NVol":"1","NVal":"1000","CVol":"242000","CVal":"242.00","broker_code":"PO","date":"21 Feb 2022"},{"Code":"BJTM","Name":"Bank Pembangunan Dae","BFreq":"","BVol":"1","BVal":"1000","BAvg":"775000","SFreq":"775.00","SVol":"1000","SVal":"775000","SAvg":"","NVol":"1","NVal":"1000","CVol":"775000","CVal":"775.00","broker_code":"PO","date":"21 Feb 2022"},{"Code":"SMGR","Name":"Semen Indonesia (Per","BFreq":"","BVol":"1","BVal":"1000","BAvg":"7.35 M","SFreq":"7350.00","SVol":"1000","SVal":"7.35 M","SAvg":"","NVol":"1","NVal":"1000","CVol":"7.35 M","CVal":"7350.00","broker_code":"PO","date":"21 Feb 2022"},{"Code":"GLOB","Name":"Globe Kita Terang Tb","BFreq":"","BVol":"1","BVal":"100","BAvg":"26800","SFreq":"268.00","SVol":"100","SVal":"26800","SAvg":"","NVol":"1","NVal":"100","CVol":"26800","CVal":"268.00","broker_code":"PO","date":"21 Feb 2022"},{"Code":"RMKE","Name":"RMK Energy Tbk.","BFreq":"3","BVol":"50000","BVal":"19.3 M","BAvg":"386.00","SFreq":"","SVol":"50000","SVal":"19.3 M","SAvg":"","NVol":"3","NVal":"50000","CVol":"19.3 M","CVal":"386.00","broker_code":"PO","date":"21 Feb 2022"},{"Code":"WSKT","Name":"Waskita Karya (Perse","BFreq":"1","BVol":"200","BVal":"124000","BAvg":"620.00","SFreq":"","SVol":"200","SVal":"124000","SAvg":"","NVol":"1","NVal":"200","CVol":"124000","CVal":"620.00","broker_code":"PO","date":"21 Feb 2022"},{"Code":"TMAS","Name":"Temas Tbk","BFreq":"5","BVol":"25000","BVal":"48.25 M","BAvg":"1930.00","SFreq":"","SVol":"25000","SVal":"48.25 M","SAvg":"","NVol":"5","NVal":"25000","CVol":"48.25 M","CVal":"1930.00","broker_code":"PO","date":"21 Feb 2022"},{"Code":"NASI","Name":"Wahana Inti Makmur T","BFreq":"1","BVol":"1000","BVal":"394000","BAvg":"394.00","SFreq":"","SVol":"1000","SVal":"394000","SAvg":"","NVol":"1","NVal":"1000","CVol":"394000","CVal":"394.00","broker_code":"PO","date":"21 Feb 2022"},{"Code":"JPFA","Name":"JAPFA Tbk","BFreq":"1","BVol":"3100","BVal":"4.94 M","BAvg":"1595.00","SFreq":"","SVol":"3100","SVal":"4.94 M","SAvg":"","NVol":"1","NVal":"3100","CVol":"4.94 M","CVal":"1595.00","broker_code":"PO","date":"21 Feb 2022"},{"Code":"NICL","Name":"PAM Mineral Tbk.","BFreq":"1","BVol":"500","BVal":"38500","BAvg":"77.00","SFreq":"","SVol":"500","SVal":"38500","SAvg":"","NVol":"1","NVal":"500","CVol":"38500","CVal":"77.00","broker_code":"PO","date":"21 Feb 2022"},{"Code":"SCMA","Name":"Surya Citra Media Tb","BFreq":"1","BVol":"100","BVal":"25600","BAvg":"256.00","SFreq":"","SVol":"100","SVal":"25600","SAvg":"","NVol":"1","NVal":"100","CVol":"25600","CVal":"256.00","broker_code":"PO","date":"21 Feb 2022"},{"Code":"IPPE","Name":"Indo Pureco Pratama","BFreq":"2","BVol":"2000","BVal":"960000","BAvg":"480.00","SFreq":"","SVol":"2000","SVal":"960000","SAvg":"","NVol":"2","NVal":"2000","CVol":"960000","CVal":"480.00","broker_code":"PO","date":"21 Feb 2022"},{"Code":"PWON","Name":"Pakuwon Jati Tbk","BFreq":"1","BVol":"700","BVal":"324800","BAvg":"464.00","SFreq":"","SVol":"700","SVal":"324800","SAvg":"","NVol":"1","NVal":"700","CVol":"324800","CVal":"464.00","broker_code":"PO","date":"21 Feb 2022"},{"Code":"BEKS","Name":"BPD Banten Tbk","BFreq":"3","BVol":"2500","BVal":"125000","BAvg":"50.00","SFreq":"","SVol":"2500","SVal":"125000","SAvg":"","NVol":"3","NVal":"2500","CVol":"125000","CVal":"50.00","broker_code":"PO","date":"21 Feb 2022"},{"Code":"VICO","Name":"Victoria Investama T","BFreq":"1","BVol":"500","BVal":"85500","BAvg":"171.00","SFreq":"","SVol":"500","SVal":"85500","SAvg":"","NVol":"1","NVal":"500","CVol":"85500","CVal":"171.00","broker_code":"PO","date":"21 Feb 2022"},{"Code":"ELSA","Name":"Elnusa Tbk","BFreq":"2","BVol":"1600","BVal":"467200","BAvg":"292.00","SFreq":"","SVol":"1600","SVal":"467200","SAvg":"","NVol":"2","NVal":"1600","CVol":"467200","CVal":"292.00","broker_code":"PO","date":"21 Feb 2022"},{"Code":"INDF","Name":"Indofood Sukses Makm","BFreq":"2","BVol":"2500","BVal":"15.7 M","BAvg":"6280.00","SFreq":"","SVol":"2500","SVal":"15.7 M","SAvg":"","NVol":"2","NVal":"2500","CVol":"15.7 M","CVal":"6280.00","broker_code":"PO","date":"21 Feb 2022"},{"Code":"MPPA","Name":"Matahari Putra Prima","BFreq":"15","BVol":"1.5 M","BVal":"452.29 M","BAvg":"301.32","SFreq":"","SVol":"1.5 M","SVal":"452.29 M","SAvg":"","NVol":"15","NVal":"1.5 M","CVol":"452.29 M","CVal":"301.32","broker_code":"PO","date":"21 Feb 2022"},{"Code":"PTPP","Name":"PP (Persero) Tbk.","BFreq":"2","BVol":"1000","BVal":"1.03 M","BAvg":"1030.00","SFreq":"","SVol":"1000","SVal":"1.03 M","SAvg":"","NVol":"2","NVal":"1000","CVol":"1.03 M","CVal":"1030.00","broker_code":"PO","date":"21 Feb 2022"},{"Code":"AYLS","Name":"Agro Yasa Lestari Tb","BFreq":"1","BVol":"9000","BVal":"2.36 M","BAvg":"262.00","SFreq":"","SVol":"9000","SVal":"2.36 M","SAvg":"","NVol":"1","NVal":"9000","CVol":"2.36 M","CVal":"262.00","broker_code":"PO","date":"21 Feb 2022"},{"Code":"CPRO","Name":"Central Proteina Pri","BFreq":"1","BVol":"300","BVal":"29400","BAvg":"98.00","SFreq":"","SVol":"300","SVal":"29400","SAvg":"","NVol":"1","NVal":"300","CVol":"29400","CVal":"98.00","broker_code":"PO","date":"21 Feb 2022"},{"Code":"SGER","Name":"Sumber Global Energy","BFreq":"29","BVol":"115000","BVal":"156.5 M","BAvg":"1360.87","SFreq":"","SVol":"115000","SVal":"156.5 M","SAvg":"","NVol":"29","NVal":"115000","CVol":"156.5 M","CVal":"1360.87","broker_code":"PO","date":"21 Feb 2022"},{"Code":"FREN","Name":"Smartfren Telecom Tb","BFreq":"1","BVol":"36000","BVal":"2.99 M","BAvg":"83.00","SFreq":"","SVol":"36000","SVal":"2.99 M","SAvg":"","NVol":"1","NVal":"36000","CVol":"2.99 M","CVal":"83.00","broker_code":"PO","date":"21 Feb 2022"},{"Code":"NOBU","Name":"Bank Nationalnobu Tb","BFreq":"1","BVol":"500","BVal":"372500","BAvg":"745.00","SFreq":"","SVol":"500","SVal":"372500","SAvg":"","NVol":"1","NVal":"500","CVol":"372500","CVal":"745.00","broker_code":"PO","date":"21 Feb 2022"},{"Code":"CASA","Name":"Capital Financial In","BFreq":"1","BVol":"6500","BVal":"3.67 M","BAvg":"565.00","SFreq":"","SVol":"6500","SVal":"3.67 M","SAvg":"","NVol":"1","NVal":"6500","CVol":"3.67 M","CVal":"565.00","broker_code":"PO","date":"21 Feb 2022"},{"Code":"JAWA","Name":"Jaya Agra Wattie Tbk","BFreq":"5","BVol":"13000","BVal":"3.17 M","BAvg":"244.00","SFreq":"","SVol":"13000","SVal":"3.17 M","SAvg":"","NVol":"5","NVal":"13000","CVol":"3.17 M","CVal":"244.00","broker_code":"PO","date":"21 Feb 2022"},{"Code":"ACES","Name":"Ace Hardware Indones","BFreq":"3","BVol":"2200","BVal":"2.67 M","BAvg":"1212.27","SFreq":"","SVol":"2200","SVal":"2.67 M","SAvg":"","NVol":"3","NVal":"2200","CVol":"2.67 M","CVal":"1212.27","broker_code":"PO","date":"21 Feb 2022"},{"Code":"BIPI","Name":"Astrindo Nusantara I","BFreq":"11","BVol":"480000","BVal":"25.92 M","BAvg":"54.00","SFreq":"","SVol":"480000","SVal":"25.92 M","SAvg":"","NVol":"11","NVal":"480000","CVol":"25.92 M","CVal":"54.00","broker_code":"PO","date":"21 Feb 2022"},{"Code":"","Name":"","BFreq":"954","BVol":"62.86 M","BVal":"51.58 B","BAvg":"1184.58","SFreq":"1354","SVol":"173.56 M","SVal":"147.95 B","SAvg":"1382.21","NVol":"60.16 M","NVal":"50.55 B","CVol":"2308","CVal":"236.42 M","TFreq":"199.53 B","TVol":"1189.97","broker_code":"PO","date":"21 Feb 2022"}]